odoo/addons/stock_landed_costs_mrp_subcontracting/README.rst
odoo/addons/stock_landed_costs_mrp_subcontracting/__init__.py
odoo/addons/stock_landed_costs_mrp_subcontracting/__manifest__.py
odoo/addons/stock_landed_costs_mrp_subcontracting/i18n/stock_landed_costs_mrp_subcontracting.pot
odoo/addons/stock_landed_costs_mrp_subcontracting/models/__init__.py
odoo/addons/stock_landed_costs_mrp_subcontracting/models/mrp_production.py
odoo/addons/stock_landed_costs_mrp_subcontracting/models/stock_landed_cost.py
odoo/addons/stock_landed_costs_mrp_subcontracting/readme/CONTRIBUTORS.rst
odoo/addons/stock_landed_costs_mrp_subcontracting/readme/DESCRIPTION.rst
odoo/addons/stock_landed_costs_mrp_subcontracting/readme/USAGE.rst
odoo/addons/stock_landed_costs_mrp_subcontracting/static/description/icon.png
odoo/addons/stock_landed_costs_mrp_subcontracting/static/description/index.html
odoo/addons/stock_landed_costs_mrp_subcontracting/tests/__init__.py
odoo/addons/stock_landed_costs_mrp_subcontracting/tests/test_stock_landed_costs_mrp_subcontracting.py
odoo14_addon_stock_landed_costs_mrp_subcontracting-14.0.1.1.0.dist-info/METADATA
odoo14_addon_stock_landed_costs_mrp_subcontracting-14.0.1.1.0.dist-info/WHEEL
odoo14_addon_stock_landed_costs_mrp_subcontracting-14.0.1.1.0.dist-info/top_level.txt
odoo14_addon_stock_landed_costs_mrp_subcontracting-14.0.1.1.0.dist-info/RECORD
